mpstats/configs/__init__.py
mpstats/configs/logger_settings.py
mpstats/database/__init__.py
mpstats/database/connectors.py
mpstats/utils/__init__.py
mpstats/utils/dynamic_loader.py
mpstats/utils/main_utils.py
mpstats/utils/stop_words.py
mpstats-0.4.0.dist-info/METADATA
mpstats-0.4.0.dist-info/WHEEL
mpstats-0.4.0.dist-info/top_level.txt
mpstats-0.4.0.dist-info/RECORD
