Metadata-Version: 2.4
Name: mpstats
Version: 0.4.0
Summary: Best bigdata python lib ever
Requires-Python: >=3.9
Requires-Dist: clickhouse-driver>=0.2.9
Requires-Dist: pandas>=2.3.0
Requires-Dist: pymongo>=4.13.2
Requires-Dist: python-dotenv>=1.1.0
Requires-Dist: requests>=2.32.5
Requires-Dist: sqlalchemy>=2.0.41
